health_records/__init__.py
health_records/grammar.lark
health_records/phr.py
health_records-0.0.7.dist-info/LICENSE
health_records-0.0.7.dist-info/METADATA
health_records-0.0.7.dist-info/WHEEL
health_records-0.0.7.dist-info/entry_points.txt
health_records-0.0.7.dist-info/top_level.txt
health_records-0.0.7.dist-info/RECORD
