Metadata-Version: 2.1
Name: health-records
Version: 0.0.7
Summary: health records
Home-page: https://github.com/pacogomez/health-records
Author: Paco Gomez
Author-email: contact@pacogomez.com
License: UNKNOWN
Project-URL: Bug Tracker, https://github.com/pacogomez/health-records/issues
Platform: UNKNOWN
Classifier: Programming Language :: Python :: 3
Classifier: License :: OSI Approved :: GNU General Public License v3 (GPLv3)
Classifier: Operating System :: OS Independent
Requires-Python: >=3.6
License-File: LICENSE
Requires-Dist: click
Requires-Dist: lark
Requires-Dist: tabulate
Requires-Dist: python-dateutil
Requires-Dist: itermplot
Requires-Dist: rich
